cscomms/__init__.py
cscomms/messaging.py
cscomms-0.0.2.dist-info/METADATA
cscomms-0.0.2.dist-info/WHEEL
cscomms-0.0.2.dist-info/licenses/LICENSE
cscomms-0.0.2.dist-info/RECORD
