Metadata-Version: 2.1
Name: cscomms
Version: 0.0.2
Summary: A python package for cross-script communication in a simple method
Project-URL: Homepage, https://example.com
Project-URL: Bug Tracker, https://example.com
Author-email: joploljojo3 <jorisblaauw12@gmail.com>
License-File: LICENSE
Classifier: License :: OSI Approved :: MIT License
Classifier: Operating System :: OS Independent
Classifier: Programming Language :: Python :: 3
Requires-Python: >=3.7
